Metadata-Version: 2.4
Name: mcp-server-beehiiv
Version: 0.1.1
Summary: Beehiiv Newsletter Subscription MCP Server using FastMCP.
Author-email: Your Name <your@email.com>
Project-URL: Homepage, https://github.com/yourusername/mcp-server-beehiiv
Requires-Python: >=3.8
Requires-Dist: fastmcp
Requires-Dist: python-dotenv
Requires-Dist: requests
